xarray_regrid/__init__.py
xarray_regrid/py.typed
xarray_regrid/regrid.py
xarray_regrid/utils.py
xarray_regrid/methods/__init__.py
xarray_regrid/methods/_shared.py
xarray_regrid/methods/conservative.py
xarray_regrid/methods/flox_reduce.py
xarray_regrid/methods/interp.py
xarray_regrid-0.4.1.dist-info/METADATA
xarray_regrid-0.4.1.dist-info/WHEEL
xarray_regrid-0.4.1.dist-info/licenses/LICENSE
xarray_regrid-0.4.1.dist-info/RECORD
