Metadata-Version: 2.4
Name: xarray-regrid
Version: 0.4.1
Summary: Regridding tools using xarray and flox.
Project-URL: Documentation, https://github.com/EXCITED-CO2/xarray-regrid#readme
Project-URL: Issues, https://github.com/EXCITED-CO2/xarray-regrid/issues
Project-URL: Source, https://github.com/EXCITED-CO2/xarray-regrid
Author-email: "Bart Schilperoort, Yang Liu" <b.schilperoort@esciencecenter.nl>
License-Expression: Apache-2.0
License-File: LICENSE
Classifier: Development Status :: 4 - Beta
Classifier: Programming Language :: Python
Classifier: Programming Language :: Python :: 3.10
Classifier: Programming Language :: Python :: 3.11
Classifier: Programming Language :: Python :: Implementation :: CPython
Classifier: Programming Language :: Python :: Implementation :: PyPy
Requires-Python: >=3.10
Requires-Dist: flox
Requires-Dist: numpy
Requires-Dist: scipy
Requires-Dist: xarray
Provides-Extra: accel
Requires-Dist: dask[distributed]; extra == 'accel'
Requires-Dist: opt-einsum; extra == 'accel'
Requires-Dist: sparse; extra == 'accel'
Provides-Extra: benchmarking
Requires-Dist: aiohttp; extra == 'benchmarking'
Requires-Dist: cftime; extra == 'benchmarking'
Requires-Dist: h5netcdf; extra == 'benchmarking'
Requires-Dist: matplotlib; extra == 'benchmarking'
Requires-Dist: pooch; extra == 'benchmarking'
Requires-Dist: requests; extra == 'benchmarking'
Requires-Dist: zarr; extra == 'benchmarking'
Provides-Extra: dev
Requires-Dist: hatch; extra == 'dev'
Requires-Dist: mypy; extra == 'dev'
Requires-Dist: pandas-stubs; extra == 'dev'
Requires-Dist: pytest; extra == 'dev'
Requires-Dist: pytest-cov; extra == 'dev'
Requires-Dist: ruff; extra == 'dev'
Provides-Extra: docs
Requires-Dist: coverage[toml]; extra == 'docs'
Requires-Dist: myst-nb; extra == 'docs'
Requires-Dist: myst-parser; extra == 'docs'
Requires-Dist: sphinx; extra == 'docs'
Requires-Dist: sphinx-autoapi; extra == 'docs'
Requires-Dist: sphinx-rtd-theme; extra == 'docs'
